<binding name="binding_100401" package="com.citic.server.dx.domain.request">
    <include path="../../custom/base-binding.xml" />
    <mapping name="Request" class="com.citic.server.dx.domain.request.CaseRequest100401">
        <structure name="Head">
            <value style="element" name="Mode" get-method="getMode" set-method="setMode" usage="optional" />
            <value style="element" name="To" get-method="getTo" set-method="setTo" usage="optional" />
            <value style="element" name="IsInitialNode" get-method="getIsInitialNode" set-method="setIsInitialNode" usage="optional" />
            <value style="element" name="FromTGOrganizationId" get-method="getFromTGOrganizationId" set-method="setFromTGOrganizationId" usage="optional" />
            <value style="element" name="TxCode" get-method="getTxCode" set-method="setTxCode" usage="optional" />
            <value style="element" name="TransSerialNumber" get-method="getTransSerialNumber" set-method="setTransSerialNumber" usage="optional" />
        </structure>
        <structure name="Body">
            <value style="element" name="ApplicationID" get-method="getApplicationID" set-method="setApplicationID" usage="optional" />
            <value style="element" name="ApplicationType" get-method="getApplicationType" set-method="setApplicationType" usage="optional" />
            <value style="element" name="ReportEndTime" get-method="getReportEndTime" set-method="setReportEndTime" usage="optional" format="toDateTime14" />
            <value style="element" name="VictimName" get-method="getVictimName" set-method="setVictimName" usage="optional" />
            <value style="element" name="VictimPhoneNumber" get-method="getVictimPhoneNumber" set-method="setVictimPhoneNumber" usage="optional" />
            <value style="element" name="VictimIDType" get-method="getVictimIDType" set-method="setVictimIDType" usage="optional" />
            <value style="element" name="VictimIDNumber" get-method="getVictimIDNumber" set-method="setVictimIDNumber" usage="optional" />
            <value style="element" name="AccidentDescription" get-method="getAccidentDescription" set-method="setAccidentDescription" usage="optional" />
            <value style="element" name="ReportOrgName" get-method="getReportOrgName" set-method="setReportOrgName" usage="optional" />
            <value style="element" name="OperatorName" get-method="getOperatorName" set-method="setOperatorName" usage="optional" />
            <value style="element" name="OperatorPhoneNumber" get-method="getOperatorPhoneNumber" set-method="setOperatorPhoneNumber" usage="optional" />
            <collection get-method="getTransactionList" set-method="setTransactionList" usage="optional" create-type="java.util.ArrayList" name="TransactionList">
                <structure type="com.citic.server.dx.domain.request.CaseRequest_Transaction" name="Transaction">
                    <value style="element" name="ID" get-method="getID" set-method="setID" usage="optional" />
                    <value style="element" name="Time" get-method="getTime" set-method="setTime" usage="optional" format="toDateTime14" />
                    <value style="element" name="Type" get-method="getType" set-method="setType" usage="optional" />
                    <value style="element" name="Currency" get-method="getCurrency" set-method="setCurrency" usage="optional" />
                    <value style="element" name="TransferAmount" get-method="getTransferAmount" set-method="setTransferAmount" usage="optional" format="noCurrency" />
                    <value style="element" name="TransferOutBankID" get-method="getTransferOutBankID" set-method="setTransferOutBankID" usage="optional" />
                    <value style="element" name="TransferOutBankName" get-method="getTransferOutBankName" set-method="setTransferOutBankName" usage="optional" format="noBlank" />
                    <value style="element" name="TransferOutAccountName" get-method="getTransferOutAccountName" set-method="setTransferOutAccountName" usage="optional" />
                    <value style="element" name="TransferOutAccountNumber" get-method="getTransferOutAccountNumber" set-method="setTransferOutAccountNumber" usage="optional" />
                    <value style="element" name="TransferInBankID" get-method="getTransferInBankID" set-method="setTransferInBankID" usage="optional" />
                    <value style="element" name="TransferInBankName" get-method="getTransferInBankName" set-method="setTransferInBankName" usage="optional" />
                    <value style="element" name="TransferInAccountName" get-method="getTransferInAccountName" set-method="setTransferInAccountName" usage="optional" />
                    <value style="element" name="TransferInAccountNumber" get-method="getTransferInAccountNumber" set-method="setTransferInAccountNumber" usage="optional" />
                    <value style="element" name="IP" get-method="getIP" set-method="setIP" usage="optional" />
                    <value style="element" name="MAC" get-method="getMAC" set-method="setMAC" usage="optional" />
                    <value style="element" name="DeviceID" get-method="getDeviceID" set-method="setDeviceID" usage="optional" />
                    <value style="element" name="Place" get-method="getPlace" set-method="setPlace" usage="optional" />
                    <value style="element" name="Remark" get-method="getRemark" set-method="setRemark" usage="optional" />
                    <value style="element" name="IsCeased" get-method="getIsCeased" set-method="setIsCeased" usage="optional" />
                </structure>
            </collection>
            <collection get-method="getAttachments" set-method="setAttachments" usage="optional" create-type="java.util.ArrayList" name="Attachments">
                <structure type="com.citic.server.dx.domain.Attachment" name="Attachment">
                    <value style="element" name="Filename" get-method="getFilename" set-method="setFilename" usage="optional" />
                    <value style="element" name="Content" get-method="getContent" set-method="setContent" usage="optional" format="base64" />
                </structure>
            </collection>
        </structure>
    </mapping>
</binding>