<binding name="binding_control_kzqq" package="com.citic.server.gf.domain.response">
    <include path="../../../custom/base-binding.xml" />
    <mapping name="kzqq" class="com.citic.server.gf.domain.response.ControlResponse_Kzqq">
        <value style="attribute" name="BDHM" get-method="getBdhm" set-method="setBdhm" usage="optional" />
        <value style="attribute" name="LB" get-method="getLb" set-method="setLb" usage="optional" />
        <value style="attribute" name="XZ" get-method="getXz" set-method="setXz" usage="optional" />
        <value style="attribute" name="XM" get-method="getXm" set-method="setXm" usage="optional" />
        <value style="attribute" name="ZJLX" get-method="getZjlx" set-method="setZjlx" usage="optional" />
        <value style="attribute" name="DSRZJHM" get-method="getDsrzjhm" set-method="setDsrzjhm" usage="optional" />
        <value style="attribute" name="FYMC" get-method="getFymc" set-method="setFymc" usage="optional" />
        <value style="attribute" name="FYDM" get-method="getFydm" set-method="setFydm" usage="optional" />
        <value style="attribute" name="CBR" get-method="getCbr" set-method="setCbr" usage="optional" />
        <value style="attribute" name="YHDH" get-method="getYhdh" set-method="setYhdh" usage="optional" />
        <value style="attribute" name="AH" get-method="getAh" set-method="setAh" usage="optional" />
        <value style="attribute" name="GZZBH" get-method="getGzzbh" set-method="setGzzbh" usage="optional" />
        <value style="attribute" name="GWZBH" get-method="getGwzbh" set-method="setGwzbh" usage="optional" />
        <value style="attribute" name="CKH" get-method="getCkh" set-method="setCkh" usage="optional" />
        <value style="attribute" name="LXFS" get-method="getLxfs" set-method="setLxfs" usage="optional" />
        <value style="attribute" name="BEIZ" get-method="getBeiz" set-method="setBeiz" usage="optional" />
        <collection name="kzzhlist" get-method="getKzzhlist" set-method="setKzzhlist" usage="optional" create-type="java.util.ArrayList">
            <structure type="com.citic.server.gf.domain.response.ControlResponse_Kzzh" name="kzzh">
                <value style="attribute" name="CCXH" get-method="getCcxh" set-method="setCcxh" usage="optional" />
                <value style="attribute" name="KZLX" get-method="getKzlx" set-method="setKzlx" usage="optional" />
                <value style="attribute" name="KZCS" get-method="getKzcs" set-method="setKzcs" usage="optional" />
                <value style="attribute" name="KHZH" get-method="getKhzh" set-method="setKhzh" usage="optional" />
                <value style="attribute" name="GLZHHM" get-method="getGlzhhm" set-method="setGlzhhm" usage="optional" />
                <value style="attribute" name="CCLB" get-method="getCclb" set-method="setCclb" usage="optional" />
                <value style="attribute" name="KHWD" get-method="getKhwd" set-method="setKhwd" usage="optional" />
                <value style="attribute" name="KHWDDM" get-method="getKhwddm" set-method="setKhwddm" usage="optional" />
                <value style="attribute" name="ZCMC" get-method="getZcmc" set-method="setZcmc" usage="optional" />
                <value style="attribute" name="ZCLX" get-method="getZclx" set-method="setZclx" usage="optional" />
                <value style="attribute" name="CPXSZL" get-method="getCpxszl" set-method="setCpxszl" usage="optional" />
                <value style="attribute" name="DQH" get-method="getDqh" set-method="setDqh" usage="optional" />
                <value style="attribute" name="JRCPBH" get-method="getJrcpbh" set-method="setJrcpbh" usage="optional" />
                <value style="attribute" name="LCZH" get-method="getLczh" set-method="setLczh" usage="optional" />
                <value style="attribute" name="ZJHKZH" get-method="getZjhkzh" set-method="setZjhkzh" usage="optional" />
                <value style="attribute" name="JLDW" get-method="getJldw" set-method="setJldw" usage="optional" />
                <value style="attribute" name="KZNR" get-method="getKznr" set-method="setKznr" usage="optional" />
                <value style="attribute" name="BZ" get-method="getBz" set-method="setBz" usage="optional" />
                <value style="attribute" name="SE" get-method="getSe" set-method="setSe" usage="optional" format="decimalPoint2"/>
                <value style="attribute" name="JE" get-method="getJe" set-method="setJe" usage="optional" format="decimalPoint2"/>
                <value style="attribute" name="KSRQ" get-method="getKsrq" set-method="setKsrq" usage="optional" />
                <value style="attribute" name="JSRQ" get-method="getJsrq" set-method="setJsrq" usage="optional" />
                <value style="attribute" name="SFJH" get-method="getSfjh" set-method="setSfjh" usage="optional" />
                <value style="attribute" name="CKWH" get-method="getCkwh" set-method="setCkwh" usage="optional" />
                <value style="attribute" name="ZXKZHHM" get-method="getZxkzhhm" set-method="setZxkzhhm" usage="optional" />
                <value style="attribute" name="ZXKZHKHH" get-method="getZxkzhkhh" set-method="setZxkzhkhh" usage="optional" />
                <value style="attribute" name="ZXKZHKHHHH" get-method="getZxkzhkhhhh" set-method="setZxkzhkhhhh" usage="optional" />
                <value style="attribute" name="ZXKZHZH" get-method="getZxkzhzh" set-method="setZxkzhzh" usage="optional" />
                <value style="attribute" name="ZXKZHLX" get-method="getZxkzhlx" set-method="setZxkzhlx" usage="optional" />
                <value style="attribute" name="YDJDH" get-method="getYdjdh" set-method="setYdjdh" usage="optional" />
                <value style="attribute" name="YDJAH" get-method="getYdjah" set-method="setYdjah" usage="optional" />
            </structure>
        </collection>
    </mapping>
</binding>